apitokens/__init__.py
apitokens/admin.py
apitokens/apps.py
apitokens/models.py
apitokens/migrations/0001_initial.py
apitokens/migrations/__init__.py
apitokens/templates/admin/apitokens/mytoken/change_list.html
apitokens/templates/admin/apitokens/token/change_list.html
django_apitokens-0.0.3.dist-info/licenses/LICENSE
django_apitokens-0.0.3.dist-info/METADATA
django_apitokens-0.0.3.dist-info/WHEEL
django_apitokens-0.0.3.dist-info/top_level.txt
django_apitokens-0.0.3.dist-info/RECORD
