Metadata-Version: 2.4
Name: django-apitokens
Version: 0.0.3
Summary: Generate API tokens for django-restframework
Author-email: InfoSec Engineering <surface@paddypowerbetfair.com>
License: MIT
Keywords: django,api,restframework,tokens,self-service
Classifier: Development Status :: 5 - Production/Stable
Classifier: Framework :: Django
Classifier: License :: OSI Approved :: MIT License
Classifier: Intended Audience :: Developers
Classifier: Operating System :: OS Independent
Classifier: Programming Language :: Python :: 3
Classifier: Environment :: Web Environment
Classifier: Topic :: Software Development
Requires-Python: >=3.7
License-File: LICENSE
Requires-Dist: Django<6.0,>=3.1
Requires-Dist: django-rest-knox==4.2.0
Provides-Extra: dev
Requires-Dist: black==23.1.0; extra == "dev"
Requires-Dist: ruff==0.0.256; extra == "dev"
Dynamic: license-file
